alignn/__init__.py
alignn/cli.py
alignn/config.py
alignn/data.py
alignn/dataset.py
alignn/graphs.py
alignn/lmdb_dataset.py
alignn/pretrained.py
alignn/profiler.py
alignn/run_alignn_ff.py
alignn/train.py
alignn/train_alignn.py
alignn/train_props.py
alignn/utils.py
alignn/ff/__init__.py
alignn/ff/all_models_alignn.json
alignn/ff/all_models_alignn_atomwise.json
alignn/ff/calculators.py
alignn/ff/ff.py
alignn/models/__init__.py
alignn/models/alignn.py
alignn/models/alignn_atomwise.py
alignn/models/ealignn_atomwise.py
alignn/models/utils.py
alignn/scripts/__init__.py
alignn/scripts/alignn_evac.py
alignn/scripts/all_train_cgcnn.py
alignn/scripts/compare_cfid.py
alignn/scripts/cubic_mat_relax.py
alignn/scripts/defect.py
alignn/scripts/early_stopping_checker.py
alignn/scripts/ev_curve.py
alignn/scripts/ev_curve_comp.py
alignn/scripts/final_model.py
alignn/scripts/graph_viz.py
alignn/scripts/make_test_split_cross_pred.py
alignn/scripts/plot_ff_results.py
alignn/scripts/plot_phonons_ff.py
alignn/scripts/predict.py
alignn/scripts/predict_db.py
alignn/scripts/predict_db_all.py
alignn/scripts/train_all_hmof.py
alignn/scripts/train_all_hpov.py
alignn/scripts/train_all_jv.py
alignn/scripts/train_all_jv_class.py
alignn/scripts/train_all_jv_dal.py
alignn/scripts/train_all_mp.py
alignn/scripts/train_all_oqmd.py
alignn/scripts/train_all_pdbbind.py
alignn/scripts/train_all_qetb.py
alignn/scripts/train_all_qm9_jctc.py
alignn/scripts/train_all_qmof.py
alignn/scripts/train_cgcnn_repo.py
alignn/scripts/train_edos_pdos.py
alignn/scripts/train_megnet.py
alignn-2025.4.1.data/scripts/pretrained.py
alignn-2025.4.1.data/scripts/run_alignn_ff.py
alignn-2025.4.1.data/scripts/train_alignn.py
alignn-2025.4.1.dist-info/LICENSE.rst
alignn-2025.4.1.dist-info/METADATA
alignn-2025.4.1.dist-info/WHEEL
alignn-2025.4.1.dist-info/top_level.txt
alignn-2025.4.1.dist-info/RECORD
