Metadata-Version: 2.2
Name: alignn
Version: 2025.4.1
Summary: alignn
Home-page: https://github.com/usnistgov/alignn
Author: Kamal Choudhary, Brian DeCost
Author-email: kamal.choudhary@nist.gov
Classifier: Programming Language :: Python :: 3
Classifier: License :: OSI Approved :: MIT License
Classifier: Operating System :: OS Independent
Requires-Python: >=3.9
License-File: LICENSE.rst
Requires-Dist: numpy<2.0
Requires-Dist: scipy>=1.6.1
Requires-Dist: jarvis-tools>=2021.07.19
Requires-Dist: torch<=2.2.1
Requires-Dist: mpmath<=1.3.0
Requires-Dist: dgl<=1.1.1
Requires-Dist: spglib>=2.0.2
Requires-Dist: scikit-learn>=0.22.2
Requires-Dist: matplotlib>=3.4.1
Requires-Dist: tqdm>=4.60.0
Requires-Dist: pandas>=1.2.3
Requires-Dist: pydantic>=1.8.1
Requires-Dist: pydantic-settings
Requires-Dist: flake8>=3.9.1
Requires-Dist: pycodestyle>=2.7.0
Requires-Dist: pydocstyle>=6.0.0
Requires-Dist: pyparsing<3,>=2.2.1
Requires-Dist: ase
Requires-Dist: lmdb
Dynamic: author
Dynamic: author-email
Dynamic: classifier
Dynamic: description
Dynamic: description-content-type
Dynamic: home-page
Dynamic: requires-dist
Dynamic: requires-python
Dynamic: summary
